hear21passt/__init__.py
hear21passt/api.py
hear21passt/base.py
hear21passt/base20sec.py
hear21passt/base2level.py
hear21passt/base2levelmel.py
hear21passt/base30sec.py
hear21passt/hop100base.py
hear21passt/hop100base2lvl.py
hear21passt/hop100base2lvlmel.py
hear21passt/hop160base.py
hear21passt/hop160base2lvl.py
hear21passt/hop160base2lvlmel.py
hear21passt/openmic2008.py
hear21passt/wrapper.py
hear21passt/models/__init__.py
hear21passt/models/passt.py
hear21passt/models/preprocess.py
hear21passt/models/helpers/__init__.py
hear21passt/models/helpers/vit_helpers.py
hear21passt-0.0.26.dist-info/METADATA
hear21passt-0.0.26.dist-info/WHEEL
hear21passt-0.0.26.dist-info/top_level.txt
hear21passt-0.0.26.dist-info/RECORD
