Metadata-Version: 2.1
Name: hear21passt
Version: 0.0.26
Summary: Passt pretrained model for HEAR 2021 NeurIPS Competition
Home-page: https://github.com/kkoutini/passt_hear21
Author: Khaled Koutini
Author-email: first.last@jku.at
License: Apache-2.0
Project-URL: Bug Tracker, https://github.com/kkoutini/passt_hear21/issues
Project-URL: Source Code, https://github.com/kkoutini/passt_hear21
Requires-Python: >=3.7
Requires-Dist: timm >=0.4.12
Requires-Dist: torchaudio >=0.7.0
